systemq/README.md
systemq/__init__.py
systemq/setup.py
systemq/dev/AlazarTechDigitizer.py
systemq/dev/ChipQ_AWG.py
systemq/dev/DG645.py
systemq/dev/DSA875.py
systemq/dev/FSL.py
systemq/dev/Keysight_PXI.py
systemq/dev/Keysight_PXI_AWG.py
systemq/dev/Keysight_PXI_DAQ.py
systemq/dev/LH_ADDA.py
systemq/dev/LH_DA.py
systemq/dev/LH_DC.py
systemq/dev/LH_DC_net.py
systemq/dev/LH_DDS_AD.py
systemq/dev/LH_DDS_AD2.py
systemq/dev/LH_DDS_ADDA.py
systemq/dev/LH_DDS_AD_x86.py
systemq/dev/LH_DDS_DA.py
systemq/dev/LH_DDS_DAx86v2.py
systemq/dev/LH_Trig.py
systemq/dev/NS_DDS.py
systemq/dev/NS_DDS_NEW.py
systemq/dev/NS_DDS_Z.py
systemq/dev/NS_DDS_old.py
systemq/dev/NS_QSYNC.py
systemq/dev/NetworkAnalyzer.py
systemq/dev/PG_AD.py
systemq/dev/PG_AWG.py
systemq/dev/PG_Trig.py
systemq/dev/PSG.py
systemq/dev/QC_AD.py
systemq/dev/QC_DA.py
systemq/dev/QC_DC.py
systemq/dev/RigolAWG.py
systemq/dev/SinolinkPSG.py
systemq/dev/TekAWG.py
systemq/dev/TekAWG70000A.py
systemq/dev/VirtualDevice.py
systemq/dev/ZWDX_RF_AWG.py
systemq/dev/ZWD_DDS_DA.py
systemq/dev/ZWD_MW.py
systemq/dev/ZW_AWG1000_DAx12v1.py
systemq/dev/ZW_CTP100.py
systemq/dev/ZW_RFSOC_AWG.py
systemq/dev/ZW_RFSOC_ZPULSE.py
systemq/dev/__init__.py
systemq/dev/ceyear_AWG.py
systemq/dev/common/__init__.py
systemq/dev/common/tek_seq_builder.py
systemq/dev/common/utils.py
systemq/dev/common/AlazarTechDigitizer/AlazarApi.py
systemq/dev/common/AlazarTechDigitizer/AlazarTechWrapper.py
systemq/dev/common/AlazarTechDigitizer/__init__.py
systemq/dev/common/AlazarTechDigitizer/exception.py
systemq/dev/common/Ceyear/__init__.py
systemq/dev/common/Ceyear/ceyear_1652AM_driver.py
systemq/dev/common/DDS_LH/__init__.py
systemq/dev/common/DDS_LH/clk_fout_dev_20220511.py
systemq/dev/common/DDS_LH/dds_x86_12adc_driver_20220704.py
systemq/dev/common/DDS_LH/dds_x86_driver_test.py
systemq/dev/common/DDS_LH/udp_awg_dev_20220117.py
systemq/dev/common/DDS_LH/udp_awg_driver_20211118.py
systemq/dev/common/DDS_LH/udp_awg_driver_20211123.py
systemq-1.0.0.dist-info/METADATA
systemq-1.0.0.dist-info/WHEEL
systemq-1.0.0.dist-info/top_level.txt
systemq-1.0.0.dist-info/RECORD
