Metadata-Version: 2.1
Name: systemq
Version: 1.0.0
Summary: systemq
Author: OrkeshNurbolat
Author-email: MG1922077@smail.nju.edu.cn
License: MIT
Classifier: License :: OSI Approved :: MIT License
Classifier: Programming Language :: Python :: 3.12
Classifier: Programming Language :: Python :: 3.11
Classifier: Programming Language :: Python :: 3.10
Classifier: Programming Language :: Python :: 3.9
Classifier: Programming Language :: Python :: 3.8
Classifier: Operating System :: OS Independent
Requires-Python: >=3.8
Requires-Dist: blinker >=1.4
Requires-Dist: pyvisa >=1.11.0
Requires-Dist: pyserial >=3.5.0
Requires-Dist: waveforms >=1.9.0
Requires-Dist: waveforms-math >=1.0.0
Requires-Dist: qlisp ==1.0.5
Requires-Dist: qlispc
Requires-Dist: cryptography
Requires-Dist: systemqmonitor >=1.0.0
Requires-Dist: qcirc >=1.0.0
Requires-Dist: requests
Requires-Dist: pandas
Requires-Dist: sqlalchemy
Requires-Dist: vios
Requires-Dist: portalocker
Requires-Dist: ipywidgets
Provides-Extra: dev
Requires-Dist: pytest >=7.0 ; extra == 'dev'
Requires-Dist: twine >=4.0.2 ; extra == 'dev'
